AUTHORS
LICENSE
MANIFEST.in
README.rst
setup.py
django_profile.egg-info/PKG-INFO
django_profile.egg-info/SOURCES.txt
django_profile.egg-info/dependency_links.txt
django_profile.egg-info/not-zip-safe
django_profile.egg-info/requires.txt
django_profile.egg-info/top_level.txt
profile/__init__.py
profile/admin.py
profile/forms.py
profile/models.py
profile/utils.py
profile/backends/__init__.py
profile/backends/simple/__init__.py
profile/backends/simple/urls.py
profile/fixtures/photosizes.json
profile/templates/profile/inclusion_tags/avatar.html
profile/templatetags/__init__.py
profile/templatetags/profile_inclusion_tags.py